{
  "works": [
    {
      "id": 1,
      "title": {
        "en-US": "This website!",
        "ru-1": "Этот вебсайт!"
      },
      "tags": [
        ["tag_website", "language"],
        ["tag_frontend", "web_asset"],
        ["tag_design", "brush"]
      ],
      "rating": 8,
      "hidden": false,
      "thumbnail": "testcommS-3",
      "imgPaths": [
        "testcommS-1",
        "testcommS-2",
        "testcommS-2",
        "testcommS-2",
        "testcommS-2"
      ],
      "descriptionShort": {
        "en-US": "I did this and that!",
        "ru-1": "Сайт-портфолио на фреймворке Quasar. Разработка дизайна, верстки и внутренней работы сайта, а также хостинг на GitHub Pages."
      },
      "descriptionLong": {
        "en-US": "I did this and that sa dasd aw dad sd asdq dwqd aqd wsd qawdqw d!",
        "ru-1": [
          [
            "work_dialog_inner_textAndPicture",
            [
              "Я сделал и то и это вфыфы в цвй вц йцв йцв ывй ыфв фв ыфв ы в! Если строка пустая, то див не создаётся",
              "fw-normal",
              "font-size:18vw",
              "testcommS-1",
              "rounded-borders",
              "width:300px"
            ]
          ],
          [
            "work_dialog_inner_textOnly",
            [
              "Я сделал и то и это вфыфы в цвй вц йцв йцв ывй ыфв фв ыфв ы в! Если строка пустая, то див не создаётся",
              "fw-normal",
              "font-size:18vw",
              "testcommS-1",
              "rounded-borders",
              "width:300px"
            ]
          ],
          [
            "work_dialog_inner_PictureAndText",
            [
              "Я сделал и то и это вфыфы в цвй вц йцв йцв ывй ыфв фв ыфв ы в! Если строка пустая, то див не создаётся",
              "fw-normal",
              "font-size:18vw",
              "testcommS-1",
              "rounded-borders",
              "width:300px"
            ]
          ],
          [
            "work_dialog_inner_PictureOnly",
            [
              "Я сделал и то и это вфыфы в цвй вц йцв йцв ывй ыфв фв ыфв ы в! Если строка пустая, то див не создаётся",
              "fw-normal",
              "font-size:18vw",
              "testcommS-1",
              "rounded-borders",
              "width:300px"
            ]
          ]
        ]
      }
    },
    {
      "id": 2,
      "title": {
        "en-US": "Logo 1 for a client",
        "ru-1": "Пример - Лого 1 для клиента"
      },
      "tags": [
        ["tag_logo", "diamond"],
        ["tag_graphics_and_vector", "diamond"],
        ["tag_design", "brush"]
      ],
      "rating": 9,
      "hidden": true,
      "thumbnail": "testcommS-3",
      "imgPaths": ["testcommS-3", "testcommS-3"],
      "descriptionShort": {
        "en-US": "I did this and that!",
        "ru-1": "Я сделал и то и это!"
      },
      "descriptionLong": {
        "en-US": "I did this and that sa dasd aw dad sd asdq dwqd aqd wsd qawdqw d!",
        "ru-1": [
          [
            "work_dialog_inner_textAndPicture",
            [
              "Я сделал и то и это вфыфы в цвй вц йцв йцв ывй ыфв фв ыфв ы в! Если строка пустая, то див не создаётся",
              "fw-normal",
              "font-size:18vw",
              "testcommS-1",
              "rounded-borders",
              "width:300px"
            ]
          ],
          [
            "work_dialog_inner_textOnly",
            [
              "Я сделал и то и это вфыфы в цвй вц йцв йцв ывй ыфв фв ыфв ы в! Если строка пустая, то див не создаётся",
              "fw-normal",
              "font-size:18vw",
              "testcommS-1",
              "rounded-borders",
              "width:300px"
            ]
          ],
          [
            "work_dialog_inner_PictureAndText",
            [
              "Я сделал и то и это вфыфы в цвй вц йцв йцв ывй ыфв фв ыфв ы в! Если строка пустая, то див не создаётся",
              "fw-normal",
              "font-size:18vw",
              "testcommS-1",
              "rounded-borders",
              "width:300px"
            ]
          ],
          [
            "work_dialog_inner_PictureOnly",
            [
              "Я сделал и то и это вфыфы в цвй вц йцв йцв ывй ыфв фв ыфв ы в! Если строка пустая, то див не создаётся",
              "fw-normal",
              "font-size:18vw",
              "testcommS-1",
              "rounded-borders",
              "width:300px"
            ]
          ]
        ]
      }
    },
    {
      "id": 3,
      "title": {
        "en-US": "Logo 2 for a client",
        "ru-1": "Пример - Лого 2 для клиента"
      },
      "tags": [
        ["tag_website", "language"],
        ["tag_frontend", "web_asset"],
        ["tag_design", "brush"],
        ["tag_no_code", "code_off"],
        ["tag_tilda", "code_off"]
      ],
      "rating": 10,
      "hidden": true,
      "thumbnail": "testcommS-3",
      "imgPaths": ["testcommS-3", "testcommS-3"],
      "descriptionShort": {
        "en-US": "I did this and that!",
        "ru-1": "Я сделал и то и это!"
      },
      "descriptionLong": {
        "en-US": "I did this and that sa dasd aw dad sd asdq dwqd aqd wsd qawdqw d!",
        "ru-1": [
          [
            "work_dialog_inner_textAndPicture",
            [
              "Я сделал и то и это вфыфы в цвй вц йцв йцв ывй ыфв фв ыфв ы в! Если строка пустая, то див не создаётся",
              "fw-normal",
              "font-size:18vw",
              "testcommS-1",
              "rounded-borders",
              "width:300px"
            ]
          ],
          [
            "work_dialog_inner_textOnly",
            [
              "Я сделал и то и это вфыфы в цвй вц йцв йцв ывй ыфв фв ыфв ы в! Если строка пустая, то див не создаётся",
              "fw-normal",
              "font-size:18vw",
              "testcommS-1",
              "rounded-borders",
              "width:300px"
            ]
          ],
          [
            "work_dialog_inner_PictureAndText",
            [
              "Я сделал и то и это вфыфы в цвй вц йцв йцв ывй ыфв фв ыфв ы в! Если строка пустая, то див не создаётся",
              "fw-normal",
              "font-size:18vw",
              "testcommS-1",
              "rounded-borders",
              "width:300px"
            ]
          ],
          [
            "work_dialog_inner_PictureOnly",
            [
              "Я сделал и то и это вфыфы в цвй вц йцв йцв ывй ыфв фв ыфв ы в! Если строка пустая, то див не создаётся",
              "fw-normal",
              "font-size:18vw",
              "testcommS-1",
              "rounded-borders",
              "width:300px"
            ]
          ]
        ]
      }
    },
    {
      "id": 4,
      "title": {
        "en-US": "Logo 2 for a client",
        "ru-1": "Пример - Лого 2 для клиента"
      },
      "tags": [
        ["tag_website", "language"],
        ["tag_frontend", "web_asset"],
        ["tag_design", "brush"],
        ["tag_no_code", "code_off"],
        ["tag_tilda", "code_off"]
      ],
      "rating": 10,
      "hidden": true,
      "thumbnail": "testcommS-3",
      "imgPaths": ["testcommS-3", "testcommS-3"],
      "descriptionShort": {
        "en-US": "I did this and that!",
        "ru-1": "Я сделал и то и это!"
      },
      "descriptionLong": {
        "en-US": "I did this and that sa dasd aw dad sd asdq dwqd aqd wsd qawdqw d!",
        "ru-1": [
          [
            "work_dialog_inner_textAndPicture",
            [
              "Я сделал и то и это вфыфы в цвй вц йцв йцв ывй ыфв фв ыфв ы в! Если строка пустая, то див не создаётся",
              "fw-normal",
              "font-size:18vw",
              "testcommS-1",
              "rounded-borders",
              "width:300px"
            ]
          ],
          [
            "work_dialog_inner_textOnly",
            [
              "Я сделал и то и это вфыфы в цвй вц йцв йцв ывй ыфв фв ыфв ы в! Если строка пустая, то див не создаётся",
              "fw-normal",
              "font-size:18vw",
              "testcommS-1",
              "rounded-borders",
              "width:300px"
            ]
          ],
          [
            "work_dialog_inner_PictureAndText",
            [
              "Я сделал и то и это вфыфы в цвй вц йцв йцв ывй ыфв фв ыфв ы в! Если строка пустая, то див не создаётся",
              "fw-normal",
              "font-size:18vw",
              "testcommS-1",
              "rounded-borders",
              "width:300px"
            ]
          ],
          [
            "work_dialog_inner_PictureOnly",
            [
              "Я сделал и то и это вфыфы в цвй вц йцв йцв ывй ыфв фв ыфв ы в! Если строка пустая, то див не создаётся",
              "fw-normal",
              "font-size:18vw",
              "testcommS-1",
              "rounded-borders",
              "width:300px"
            ]
          ]
        ]
      }
    },
    {
      "id": 5,
      "title": {
        "en-US": "Logo 2 for a client",
        "ru-1": "Пример - Лого 2 для клиента"
      },
      "tags": [
        ["tag_website", "language"],
        ["tag_frontend", "web_asset"],
        ["tag_design", "brush"],
        ["tag_no_code", "code_off"],
        ["tag_tilda", "code_off"]
      ],
      "rating": 10,
      "hidden": true,
      "thumbnail": "testcommS-3",
      "imgPaths": ["testcommS-3", "testcommS-3"],
      "descriptionShort": {
        "en-US": "I did this and that!",
        "ru-1": "Я сделал и то и это!"
      },
      "descriptionLong": {
        "en-US": "I did this and that sa dasd aw dad sd asdq dwqd aqd wsd qawdqw d!",
        "ru-1": [
          [
            "work_dialog_inner_textAndPicture",
            [
              "Я сделал и то и это вфыфы в цвй вц йцв йцв ывй ыфв фв ыфв ы в! Если строка пустая, то див не создаётся",
              "fw-normal",
              "font-size:18vw",
              "testcommS-1",
              "rounded-borders",
              "width:300px"
            ]
          ],
          [
            "work_dialog_inner_textOnly",
            [
              "Я сделал и то и это вфыфы в цвй вц йцв йцв ывй ыфв фв ыфв ы в! Если строка пустая, то див не создаётся",
              "fw-normal",
              "font-size:18vw",
              "testcommS-1",
              "rounded-borders",
              "width:300px"
            ]
          ],
          [
            "work_dialog_inner_PictureAndText",
            [
              "Я сделал и то и это вфыфы в цвй вц йцв йцв ывй ыфв фв ыфв ы в! Если строка пустая, то див не создаётся",
              "fw-normal",
              "font-size:18vw",
              "testcommS-1",
              "rounded-borders",
              "width:300px"
            ]
          ],
          [
            "work_dialog_inner_PictureOnly",
            [
              "Я сделал и то и это вфыфы в цвй вц йцв йцв ывй ыфв фв ыфв ы в! Если строка пустая, то див не создаётся",
              "fw-normal",
              "font-size:18vw",
              "testcommS-1",
              "rounded-borders",
              "width:300px"
            ]
          ]
        ]
      }
    },
    {
      "id": 6,
      "title": {
        "en-US": "Product cards - accessories for strikeball",
        "ru-1": "Карточки товара - акссесуары для страйкбола"
      },
      "tags": [
        ["tag_graphics_and_vector", "diamond"],
        ["tag_design", "brush"]
      ],
      "rating": 8,
      "hidden": false,
      "thumbnail": "marketcard_strikeball1_1",
      "imgPaths": [
        "marketcard_strikeball1_1",
        "marketcard_strikeball1_2",
        "marketcard_strikeball1_3",
        "marketcard_strikeball1_4"
      ],
      "descriptionShort": {
        "en-US": "I did this and that!",
        "ru-1": "Дизайн карт продукта для маркетплейса Ozon - акссесуары для страйкбола"
      },
      "descriptionLong": {
        "en-US": "Дизайн карт продукта для маркетплейса Ozon - акссесуары для страйкбола. Дизайн карт продукта для маркетплейса Ozon - акссесуары для страйкбола",
        "ru-1": [
          [
            "work_dialog_inner_textAndPicture",
            [
              "Я сделал и то и это вфыфы в цвй вц йцв йцв ывй ыфв фв ыфв ы в! Если строка пустая, то див не создаётся",
              "fw-normal",
              "font-size:18vw",
              "testcommS-1",
              "rounded-borders",
              "width:300px"
            ]
          ],
          [
            "work_dialog_inner_textOnly",
            [
              "Я сделал и то и это вфыфы в цвй вц йцв йцв ывй ыфв фв ыфв ы в! Если строка пустая, то див не создаётся",
              "fw-normal",
              "font-size:18vw",
              "testcommS-1",
              "rounded-borders",
              "width:300px"
            ]
          ],
          [
            "work_dialog_inner_PictureAndText",
            [
              "Я сделал и то и это вфыфы в цвй вц йцв йцв ывй ыфв фв ыфв ы в! Если строка пустая, то див не создаётся",
              "fw-normal",
              "font-size:18vw",
              "testcommS-1",
              "rounded-borders",
              "width:300px"
            ]
          ],
          [
            "work_dialog_inner_PictureOnly",
            [
              "Я сделал и то и это вфыфы в цвй вц йцв йцв ывй ыфв фв ыфв ы в! Если строка пустая, то див не создаётся",
              "fw-normal",
              "font-size:18vw",
              "testcommS-1",
              "rounded-borders",
              "width:300px"
            ]
          ]
        ]
      }
    },
    {
      "id": 7,
      "title": {
        "en-US": "Logo for massage studio",
        "ru-1": "Логотип для студии массажа \"Умный фитнес\""
      },
      "tags": [
        ["tag_logo", "diamond"],
        ["tag_graphics_and_vector", "diamond"],
        ["tag_design", "brush"]
      ],
      "rating": 9,
      "hidden": false,
      "thumbnail": "logo_massageStudio1_1",
      "imgPaths": ["logo_massageStudio1_1"],
      "descriptionShort": {
        "en-US": "I did this and that!",
        "ru-1": "Логотип для студии массажа \"Умный фитнес\", созданный по пожеланиям заказчика"
      },
      "descriptionLong": {
        "en-US": "Логотип для студии массажа \"Умный фитнес\", созданный по пожеланиям заказчика. Логотип для студии массажа \"Умный фитнес\", созданный по пожеланиям заказчика.",
        "ru-1": [
          [
            "work_dialog_inner_textAndPicture",
            [
              "Я сделал и то и это вфыфы в цвй вц йцв йцв ывй ыфв фв ыфв ы в! Если строка пустая, то див не создаётся",
              "fw-normal",
              "font-size:18vw",
              "testcommS-1",
              "rounded-borders",
              "width:300px"
            ]
          ],
          [
            "work_dialog_inner_textOnly",
            [
              "Я сделал и то и это вфыфы в цвй вц йцв йцв ывй ыфв фв ыфв ы в! Если строка пустая, то див не создаётся",
              "fw-normal",
              "font-size:18vw",
              "testcommS-1",
              "rounded-borders",
              "width:300px"
            ]
          ],
          [
            "work_dialog_inner_PictureAndText",
            [
              "Я сделал и то и это вфыфы в цвй вц йцв йцв ывй ыфв фв ыфв ы в! Если строка пустая, то див не создаётся",
              "fw-normal",
              "font-size:18vw",
              "testcommS-1",
              "rounded-borders",
              "width:300px"
            ]
          ],
          [
            "work_dialog_inner_PictureOnly",
            [
              "Я сделал и то и это вфыфы в цвй вц йцв йцв ывй ыфв фв ыфв ы в! Если строка пустая, то див не создаётся",
              "fw-normal",
              "font-size:18vw",
              "testcommS-1",
              "rounded-borders",
              "width:300px"
            ]
          ]
        ]
      }
    },
    {
      "id": 8,
      "title": {
        "en-US": "Logo for furniture company",
        "ru-1": "Логотип для мебельной компании \"Вам Дам Мебель\""
      },
      "tags": [
        ["tag_logo", "diamond"],
        ["tag_graphics_and_vector", "diamond"],
        ["tag_design", "brush"]
      ],
      "rating": 9,
      "hidden": false,
      "thumbnail": "logo_furniture1_1",
      "imgPaths": ["logo_furniture1_1"],
      "descriptionShort": {
        "en-US": "I did this and that!",
        "ru-1": "Логотип для мебельной компании \"Вам Дам Мебель\", созданный по пожеланиям заказчика"
      },
      "descriptionLong": {
        "en-US": "Можно сделать блоки с процессом работы, которые будут прогружаться из тегов.",
        "ru-1": [
          [
            "work_dialog_inner_textAndPicture",
            [
              "Я сделал и то и это вфыфы в цвй вц йцв йцв ывй ыфв фв ыфв ы в! Если строка пустая, то див не создаётся",
              "fw-normal",
              "font-size:18vw",
              "testcommS-1",
              "rounded-borders",
              "width:300px"
            ]
          ],
          [
            "work_dialog_inner_textOnly",
            [
              "Я сделал и то и это вфыфы в цвй вц йцв йцв ывй ыфв фв ыфв ы в! Если строка пустая, то див не создаётся",
              "fw-normal",
              "font-size:18vw",
              "testcommS-1",
              "rounded-borders",
              "width:300px"
            ]
          ],
          [
            "work_dialog_inner_PictureAndText",
            [
              "Я сделал и то и это вфыфы в цвй вц йцв йцв ывй ыфв фв ыфв ы в! Если строка пустая, то див не создаётся",
              "fw-normal",
              "font-size:18vw",
              "testcommS-1",
              "rounded-borders",
              "width:300px"
            ]
          ],
          [
            "work_dialog_inner_PictureOnly",
            [
              "Я сделал и то и это вфыфы в цвй вц йцв йцв ывй ыфв фв ыфв ы в! Если строка пустая, то див не создаётся",
              "fw-normal",
              "font-size:18vw",
              "testcommS-1",
              "rounded-borders",
              "width:300px"
            ]
          ]
        ]
      }
    }
  ],

  "services_TODO_FROM_KWORK": [
    {
      "id": 1,
      "title": {
        "en-US": "Website on Tilda or WordPress",
        "ru-1": "Вебсайт на Тильда или Вордпресс"
      },
      "tags": [
        ["tag_website", "language"],
        ["tag_frontend", "web_asset"],
        ["tag_design", "brush"],
        ["tag_tilda", "code_off"],
        ["tag_wordpress", "code_off"]
      ],
      "rating": 6,
      "priceUS": 80,
      "priceRU": 4000,
      "hidden": false,
      "thumbnail": "testcommS-3",
      "imgPaths": ["testcommS-3", "testcommS-3"],
      "descriptionShort": {
        "en-US": "I did this and that!",
        "ru-1": "Я сделал и то и это!"
      },
      "descriptionLong": {
        "en-US": "I did this and that sa dasd aw dad sd asdq dwqd aqd wsd qawdqw d!",
        "ru-1": [
          [
            "work_dialog_inner_textAndPicture",
            [
              "Я сделал и то и это вфыфы в цвй вц йцв йцв ывй ыфв фв ыфв ы в! Если строка пустая, то див не создаётся",
              "fw-normal",
              "font-size:18vw",
              "testcommS-1",
              "rounded-borders",
              "width:300px"
            ]
          ],
          [
            "work_dialog_inner_textOnly",
            [
              "Я сделал и то и это вфыфы в цвй вц йцв йцв ывй ыфв фв ыфв ы в! Если строка пустая, то див не создаётся",
              "fw-normal",
              "font-size:18vw",
              "testcommS-1",
              "rounded-borders",
              "width:300px"
            ]
          ],
          [
            "work_dialog_inner_PictureAndText",
            [
              "Я сделал и то и это вфыфы в цвй вц йцв йцв ывй ыфв фв ыфв ы в! Если строка пустая, то див не создаётся",
              "fw-normal",
              "font-size:18vw",
              "testcommS-1",
              "rounded-borders",
              "width:300px"
            ]
          ],
          [
            "work_dialog_inner_PictureOnly",
            [
              "Я сделал и то и это вфыфы в цвй вц йцв йцв ывй ыфв фв ыфв ы в! Если строка пустая, то див не создаётся",
              "fw-normal",
              "font-size:18vw",
              "testcommS-1",
              "rounded-borders",
              "width:300px"
            ]
          ]
        ]
      }
    },
    {
      "id": 2,
      "title": {
        "en-US": "Vector Logo",
        "ru-1": "Векторное Лого"
      },
      "tags": [
        ["tag_logo", "diamond"],
        ["tag_graphics_and_vector", "diamond"],
        ["tag_design", "brush"]
      ],
      "rating": 10,
      "priceUS": 40,
      "priceRU": 2000,
      "hidden": false,
      "thumbnail": "testcommS-3",
      "imgPaths": ["testcommS-3", "testcommS-3"],
      "descriptionShort": {
        "en-US": "I did this and that!",
        "ru-1": "Я сделал и то и это!"
      },
      "descriptionLong": {
        "en-US": "I did this and that sa dasd aw dad sd asdq dwqd aqd wsd qawdqw d!",
        "ru-1": [
          [
            "work_dialog_inner_textAndPicture",
            [
              "Я сделал и то и это вфыфы в цвй вц йцв йцв ывй ыфв фв ыфв ы в! Если строка пустая, то див не создаётся",
              "fw-normal",
              "font-size:18vw",
              "testcommS-1",
              "rounded-borders",
              "width:300px"
            ]
          ],
          [
            "work_dialog_inner_textOnly",
            [
              "Я сделал и то и это вфыфы в цвй вц йцв йцв ывй ыфв фв ыфв ы в! Если строка пустая, то див не создаётся",
              "fw-normal",
              "font-size:18vw",
              "testcommS-1",
              "rounded-borders",
              "width:300px"
            ]
          ],
          [
            "work_dialog_inner_PictureAndText",
            [
              "Я сделал и то и это вфыфы в цвй вц йцв йцв ывй ыфв фв ыфв ы в! Если строка пустая, то див не создаётся",
              "fw-normal",
              "font-size:18vw",
              "testcommS-1",
              "rounded-borders",
              "width:300px"
            ]
          ],
          [
            "work_dialog_inner_PictureOnly",
            [
              "Я сделал и то и это вфыфы в цвй вц йцв йцв ывй ыфв фв ыфв ы в! Если строка пустая, то див не создаётся",
              "fw-normal",
              "font-size:18vw",
              "testcommS-1",
              "rounded-borders",
              "width:300px"
            ]
          ]
        ]
      }
    },
    {
      "id": 3,
      "title": {
        "en-US": "Logo 2 for a client",
        "ru-1": "Лого 2 для клиента"
      },
      "tags": [
        ["tag_website", "language"],
        ["tag_frontend", "web_asset"],
        ["tag_design", "brush"],
        ["tag_no_code", "code_off"],
        ["tag_tilda", "code_off"]
      ],
      "rating": 10,
      "priceUS": 40,
      "priceRU": 2000,
      "hidden": true,
      "thumbnail": "testcommS-3",
      "imgPaths": ["testcommS-3", "testcommS-3"],
      "descriptionShort": {
        "en-US": "I did this and that!",
        "ru-1": "Я сделал и то и это!"
      },
      "descriptionLong": {
        "en-US": [
          [
            "BIT TEXT",
            "I did this and that sa dasd aw dad sd asdq dwqd aqd wsd qawdqw d!"
          ],
          [
            "BIT TEXT2",
            "I did this and that sa dasd aw dad sd asdq dwqd aqd wsd qawdqw d!"
          ]
        ],
        "ru-1": [
          [
            "work_dialog_inner_textAndPicture",
            [
              "Я сделал и то и это вфыфы в цвй вц йцв йцв ывй ыфв фв ыфв ы в! Если строка пустая, то див не создаётся",
              "fw-normal",
              "font-size:18vw",
              "testcommS-1",
              "rounded-borders",
              "width:300px"
            ]
          ],
          [
            "work_dialog_inner_textOnly",
            [
              "Я сделал и то и это вфыфы в цвй вц йцв йцв ывй ыфв фв ыфв ы в! Если строка пустая, то див не создаётся",
              "fw-normal",
              "font-size:18vw",
              "testcommS-1",
              "rounded-borders",
              "width:300px"
            ]
          ],
          [
            "work_dialog_inner_PictureAndText",
            [
              "Я сделал и то и это вфыфы в цвй вц йцв йцв ывй ыфв фв ыфв ы в! Если строка пустая, то див не создаётся",
              "fw-normal",
              "font-size:18vw",
              "testcommS-1",
              "rounded-borders",
              "width:300px"
            ]
          ],
          [
            "work_dialog_inner_PictureOnly",
            [
              "Я сделал и то и это вфыфы в цвй вц йцв йцв ывй ыфв фв ыфв ы в! Если строка пустая, то див не создаётся",
              "fw-normal",
              "font-size:18vw",
              "testcommS-1",
              "rounded-borders",
              "width:300px"
            ]
          ]
        ]
      }
    }
  ]
}
